arnold/__init__.py
arnold/exceptions.py
arnold/models.py
arnold-0.4.1.dist-info/DESCRIPTION.rst
arnold-0.4.1.dist-info/METADATA
arnold-0.4.1.dist-info/RECORD
arnold-0.4.1.dist-info/WHEEL
arnold-0.4.1.dist-info/entry_points.txt
arnold-0.4.1.dist-info/metadata.json
arnold-0.4.1.dist-info/top_level.txt
