Metadata-Version: 2.0
Name: arnold
Version: 0.4.1
Summary: Simple migrations for python ORMs
Home-page: https://github.com/cam-stitt/arnold
Author: Cameron A. Stitt
Author-email: cameron@castitt.com
License: BSD
Keywords: python,peewee,migrations
Platform: UNKNOWN
Classifier: Programming Language :: Python
Classifier: Topic :: Software Development :: Libraries :: Python Modules
Requires-Dist: peewee
Requires-Dist: termcolor
